{
  "layerFile": "neck_double_breasted+buttons_6+lapel_narrow+style_lapel_peak.png",
  "zones": [
    {
      "polygon": [
        [
          226,
          118
        ],
        [
          236,
          90
        ],
        [
          259,
          60
        ],
        [
          260,
          82
        ],
        [
          275,
          134
        ],
        [
          291,
          183
        ],
        [
          301,
          220
        ],
        [
          308,
          246
        ],
        [
          292,
          288
        ],
        [
          262,
          226
        ],
        [
          233,
          171
        ],
        [
          210,
          109
        ],
        [
          224,
          115
        ]
      ],
      "rotation": -27.0
    },
    {
      "polygon": [
        [
          272,
          351
        ],
        [
          300,
          323
        ],
        [
          333,
          270
        ],
        [
          365,
          209
        ],
        [
          392,
          156
        ],
        [
          414,
          108
        ],
        [
          395,
          112
        ],
        [
          390,
          89
        ],
        [
          374,
          66
        ],
        [
          366,
          52
        ],
        [
          366,
          85
        ],
        [
          343,
          149
        ],
        [
          325,
          197
        ],
        [
          308,
          253
        ],
        [
          289,
          296
        ],
        [
          280,
          325
        ],
        [
          272,
          349
        ]
      ],
      "rotation": 29.0
    }
  ]
}
